mir/protology.py
mir/sqlqs/__init__.py
mir/sqlqs/amigration.py
mir/sqlqs/apragma.py
mir/sqlqs/migration.py
mir/sqlqs/pragma.py
mir/sqlqs/queryset.py
mir.sqlqs-0.4.0.dist-info/DESCRIPTION.rst
mir.sqlqs-0.4.0.dist-info/METADATA
mir.sqlqs-0.4.0.dist-info/RECORD
mir.sqlqs-0.4.0.dist-info/WHEEL
mir.sqlqs-0.4.0.dist-info/metadata.json
mir.sqlqs-0.4.0.dist-info/top_level.txt
