Metadata-Version: 2.0
Name: mir.sqlqs
Version: 0.4.0
Summary: Relational SQL API (SQL QuerySet)
Home-page: https://github.com/darkfeline/mir.sqlqs
Author: Allen Li
Author-email: darkfeline@felesatra.moe
License: UNKNOWN
Platform: UNKNOWN
Classifier: Development Status :: 3 - Alpha
Classifier: Intended Audience :: Developers
Classifier: License :: OSI Approved :: Apache Software License
Classifier: Programming Language :: Python :: 3.6
Requires-Dist: SQLAlchemy
Requires-Dist: apsw
